odoo/addons/membership_extension/README.rst
odoo/addons/membership_extension/__init__.py
odoo/addons/membership_extension/__manifest__.py
odoo/addons/membership_extension/data/membership_category_data.xml
odoo/addons/membership_extension/demo/membership_category_demo.xml
odoo/addons/membership_extension/demo/product_template_demo.xml
odoo/addons/membership_extension/i18n/am.po
odoo/addons/membership_extension/i18n/ar.po
odoo/addons/membership_extension/i18n/bg.po
odoo/addons/membership_extension/i18n/bs.po
odoo/addons/membership_extension/i18n/ca.po
odoo/addons/membership_extension/i18n/cs.po
odoo/addons/membership_extension/i18n/da.po
odoo/addons/membership_extension/i18n/de.po
odoo/addons/membership_extension/i18n/el_GR.po
odoo/addons/membership_extension/i18n/en_GB.po
odoo/addons/membership_extension/i18n/es.po
odoo/addons/membership_extension/i18n/es_AR.po
odoo/addons/membership_extension/i18n/es_CL.po
odoo/addons/membership_extension/i18n/es_CO.po
odoo/addons/membership_extension/i18n/es_CR.po
odoo/addons/membership_extension/i18n/es_DO.po
odoo/addons/membership_extension/i18n/es_EC.po
odoo/addons/membership_extension/i18n/es_ES.po
odoo/addons/membership_extension/i18n/es_MX.po
odoo/addons/membership_extension/i18n/es_PE.po
odoo/addons/membership_extension/i18n/es_PY.po
odoo/addons/membership_extension/i18n/es_VE.po
odoo/addons/membership_extension/i18n/et.po
odoo/addons/membership_extension/i18n/fa.po
odoo/addons/membership_extension/i18n/fi.po
odoo/addons/membership_extension/i18n/fr.po
odoo/addons/membership_extension/i18n/fr_CA.po
odoo/addons/membership_extension/i18n/fr_CH.po
odoo/addons/membership_extension/i18n/fr_FR.po
odoo/addons/membership_extension/i18n/gl.po
odoo/addons/membership_extension/i18n/gl_ES.po
odoo/addons/membership_extension/i18n/he.po
odoo/addons/membership_extension/i18n/hr.po
odoo/addons/membership_extension/i18n/hr_HR.po
odoo/addons/membership_extension/i18n/hu.po
odoo/addons/membership_extension/i18n/id.po
odoo_addon_membership_extension-18.0.1.0.0.2.dist-info/METADATA
odoo_addon_membership_extension-18.0.1.0.0.2.dist-info/WHEEL
odoo_addon_membership_extension-18.0.1.0.0.2.dist-info/top_level.txt
odoo_addon_membership_extension-18.0.1.0.0.2.dist-info/RECORD
